[
    {
        "content": "<p>I just created an account on <a href=\"https://stoat.chat\">https://stoat.chat</a></p>\n<p>Has anyone else heard of it? What do you think?</p>\n<p>See also <a href=\"https://github.com/stoatchat\">https://github.com/stoatchat</a> and <a href=\"https://en.wikipedia.org/wiki/Stoat_(software)\">https://en.wikipedia.org/wiki/Stoat_(software)</a></p>",
        "id": 573655799,
        "sender_full_name": "Philip Durbin",
        "timestamp": 1770952306
    },
    {
        "content": "<p>Their website doesn't help explain what it is.</p>",
        "id": 574011465,
        "sender_full_name": "Dan",
        "timestamp": 1771194107
    },
    {
        "content": "<p>I normally wouldn't like the overloading of the term \"servers\" but if it's stealing it from Discord I guess that's good.</p>",
        "id": 574011592,
        "sender_full_name": "Dan",
        "timestamp": 1771194202
    },
    {
        "content": "<p>They should have screenshots. But I guess it's like Discord, which I don't care for in the first place. But better to get people onto a FOSS alternative.</p>",
        "id": 574011630,
        "sender_full_name": "Dan",
        "timestamp": 1771194239
    }
]